{
  "COMPANY_NOTFOUND": "Không tìm thấy công ty với ID {0}",
  "COMPANY_CREATE_FAILED": "Tạo công ty thất bại",
  "COMPANY_UPDATE_FAILED": "Cập nhật công ty thất bại",
  "COMPANY_DELETE_FAILED": "Xóa công ty thất bại",
  "COMPANY_GET_ID_FAILED": "Lỗi khi truy xuất công ty theo ID",
  "COMPANY_GET_ALL_FAILED": "Lỗi khi truy xuất danh sách công ty",
  "COMPANY_GET_ACTIVE_FAILED": "Lỗi khi truy xuất danh sách công ty đang hoạt động",
  "COMPANY_GET_CODE_FAILED": "Lỗi khi truy xuất công ty theo mã",
  "COMPANY_NAME_REQUIRED": "Tên công ty là bắt buộc",
  "COMPANY_NAME_TOO_LONG": "Tên công ty không được vượt quá {0} ký tự",
  "COMPANY_CODE_DUPLICATE": "Mã công ty đã tồn tại",
  "COMPANY_DUPLICATE_CODE": "Mã công ty '{0}' đã tồn tại",
  "COMPANY_ID_MISMATCH": "ID công ty không khớp. ID trong đường dẫn {0} không khớp với ID trong nội dung yêu cầu {1}",
  "COMPANY_CONCURRENCY_CONFLICT": "Công ty đã được chỉnh sửa bởi người dùng khác. Vui lòng làm mới và thử lại",
  "COMPANY_SEARCH_FAILED": "Lỗi khi tìm kiếm công ty. Vui lòng thử lại",
  
  "USER_NOTFOUND": "Không tìm thấy người dùng với ID {0}",
  "USER_CREATE_FAILED": "Tạo người dùng thất bại",
  "USER_UPDATE_FAILED": "Cập nhật người dùng thất bại",
  "USER_DELETE_FAILED": "Xóa người dùng thất bại",
  "USER_EMAIL_REQUIRED": "Email là bắt buộc",
  "USER_EMAIL_INVALID": "Định dạng email không hợp lệ",
  "USER_EMAIL_DUPLICATE": "Email đã tồn tại",
  "USER_PASSWORD_REQUIRED": "Mật khẩu là bắt buộc",
  "USER_PASSWORD_TOO_SHORT": "Mật khẩu phải có ít nhất {0} ký tự",
  
  "AUTH_INVALID_CREDENTIALS": "Email/tên đăng nhập hoặc mật khẩu không hợp lệ",
  "AUTH_USER_NOT_FOUND": "Không tìm thấy người dùng",
  "AUTH_INVALID_PASSWORD": "Mật khẩu không hợp lệ",
  "AUTH_ACCOUNT_INACTIVE": "Tài khoản đã bị vô hiệu hóa",
  "AUTH_FAILED": "Xác thực thất bại",
  "AUTH_INVALID_ACCESS_TOKEN": "Access token không hợp lệ",
  "AUTH_INVALID_REFRESH_TOKEN": "Refresh token không hợp lệ",
  "AUTH_REFRESH_TOKEN_EXPIRED": "Refresh token đã hết hạn",
  "AUTH_INVALID_TOKEN_CLAIMS": "Thông tin token không hợp lệ",
  "AUTH_TOKEN_REFRESH_FAILED": "Làm mới token thất bại",
  "AUTH_LOGOUT_FAILED": "Đăng xuất thất bại",
  
  "AUDITLOG_NOTFOUND": "Không tìm thấy nhật ký kiểm toán với ID {0}",
  "AUDITLOG_GET_ID_FAILED": "Lỗi khi truy xuất nhật ký kiểm toán theo ID",
  "AUDITLOG_GET_PAGED_FAILED": "Lỗi khi truy xuất nhật ký kiểm toán",
  "AUDITLOG_GET_ENTITY_FAILED": "Lỗi khi truy xuất nhật ký kiểm toán cho đối tượng",
  "AUDITLOG_GET_COMPANY_FAILED": "Lỗi khi truy xuất nhật ký kiểm toán cho công ty",
  "AUDITLOG_GET_USER_FAILED": "Lỗi khi truy xuất nhật ký kiểm toán cho người dùng",
  "AUDITLOG_QUERY_FAILED": "Lỗi khi tìm kiếm nhật ký kiểm toán",
  "AUDITLOG_CREATE_FAILED": "Tạo nhật ký kiểm toán thất bại",
  "AUDITLOG_INVALID_DATE_RANGE": "Khoảng thời gian không hợp lệ. Ngày bắt đầu phải trước ngày kết thúc",
  
  "CUSTOMER_NOTFOUND": "Không tìm thấy khách hàng với ID {0}",
  "CUSTOMER_CREATE_FAILED": "Tạo khách hàng thất bại",
  "CUSTOMER_UPDATE_FAILED": "Cập nhật khách hàng thất bại",
  "CUSTOMER_DELETE_FAILED": "Xóa khách hàng thất bại",
  "CUSTOMER_NAME_REQUIRED": "Tên khách hàng là bắt buộc",
  "CUSTOMER_CODE_DUPLICATE": "Mã khách hàng đã tồn tại",
  
  "PRODUCT_NOTFOUND": "Không tìm thấy sản phẩm với ID {0}",
  "PRODUCT_CREATE_FAILED": "Tạo sản phẩm thất bại",
  "PRODUCT_UPDATE_FAILED": "Cập nhật sản phẩm thất bại",
  "PRODUCT_DELETE_FAILED": "Xóa sản phẩm thất bại",
  "PRODUCT_NAME_REQUIRED": "Tên sản phẩm là bắt buộc",
  "PRODUCT_SKU_DUPLICATE": "Mã SKU đã tồn tại",
  "PRODUCT_INSUFFICIENT_STOCK": "Tồn kho không đủ. Có sẵn: {0}, Yêu cầu: {1}",
  
  "ORDER_NOTFOUND": "Không tìm thấy đơn hàng với ID {0}",
  "ORDER_CREATE_FAILED": "Tạo đơn hàng thất bại",
  "ORDER_UPDATE_FAILED": "Cập nhật đơn hàng thất bại",
  "ORDER_DELETE_FAILED": "Xóa đơn hàng thất bại",
  "ORDER_NUMBER_DUPLICATE": "Số đơn hàng đã tồn tại",
  "ORDER_ITEMS_REQUIRED": "Đơn hàng phải có ít nhất một mục",
  
  "WAREHOUSE_NOTFOUND": "Không tìm thấy kho với ID {0}",
  "WAREHOUSE_CREATE_FAILED": "Tạo kho thất bại",
  "WAREHOUSE_UPDATE_FAILED": "Cập nhật kho thất bại",
  "WAREHOUSE_DELETE_FAILED": "Xóa kho thất bại",
  "WAREHOUSE_NAME_REQUIRED": "Tên kho là bắt buộc",
  "WAREHOUSE_CODE_DUPLICATE": "Mã kho đã tồn tại",
  
  "VALIDATION_FAILED": "Xác thực thất bại",
  "VALIDATION_REQUIRED": "Trường này là bắt buộc",
  "VALIDATION_INVALID_FORMAT": "Định dạng không hợp lệ",
  "VALIDATION_TOO_LONG": "Giá trị quá dài",
  "VALIDATION_TOO_SHORT": "Giá trị quá ngắn",
  "VALIDATION_EMAIL_INVALID": "Định dạng email không hợp lệ",
  "VALIDATION_MAX_LENGTH": "Không được vượt quá {0} ký tự",
  "VALIDATION_MIN_LENGTH": "Phải có ít nhất {0} ký tự",
  
  "UNAUTHORIZED": "Truy cập không được phép",
  "FORBIDDEN": "Bị cấm truy cập",
  "INTERNAL_ERROR": "Đã xảy ra lỗi nội bộ",
  "INVALID_REQUEST": "Yêu cầu không hợp lệ",
  "RESOURCE_NOT_FOUND": "Không tìm thấy tài nguyên"
}

